neo3/__init__.py
neo3/py.typed
neo3/settings.py
neo3/singleton.py
neo3/vm.py
neo3/api/__init__.py
neo3/api/noderpc.py
neo3/api/wrappers.py
neo3/api/helpers/__init__.py
neo3/api/helpers/signing.py
neo3/api/helpers/stdlib.py
neo3/api/helpers/txbuilder.py
neo3/api/helpers/unwrap.py
neo3/contracts/__init__.py
neo3/contracts/abi.py
neo3/contracts/callflags.py
neo3/contracts/contract.py
neo3/contracts/findoptions.py
neo3/contracts/manifest.py
neo3/contracts/nef.py
neo3/contracts/utils.py
neo3/core/__init__.py
neo3/core/interfaces.py
neo3/core/serialization.py
neo3/core/utils.py
neo3/core/cryptography/__init__.py
neo3/core/cryptography/bloomfilter.py
neo3/core/cryptography/ecc.py
neo3/core/cryptography/merkletree.py
neo3/core/types/__init__.py
neo3/core/types/uint.py
neo3/network/__init__.py
neo3/network/capabilities.py
neo3/network/ipfilter.py
neo3/network/message.py
neo3/network/node.py
neo3/network/relaycache.py
neo3/network/convenience/__init__.py
neo3/network/convenience/flightinfo.py
neo3/network/convenience/nodemanager.py
neo3/network/convenience/nodeweight.py
neo3/network/convenience/requestinfo.py
neo3/network/convenience/syncmanager.py
neo3/network/payloads/__init__.py
neo3/network/payloads/address.py
neo3/network/payloads/block.py
neo3/network/payloads/consensus.py
neo3/network/payloads/empty.py
neo3/network/payloads/extensible.py
neo3/network/payloads/filter.py
neo3/network/payloads/inventory.py
neo3/network/payloads/ping.py
neo3/network/payloads/transaction.py
neo3/network/payloads/verification.py
neo3/network/payloads/version.py
neo3/wallet/__init__.py
neo3/wallet/account.py
neo3/wallet/scrypt_parameters.py
neo3/wallet/types.py
neo3/wallet/utils.py
neo3/wallet/wallet.py
neo_mamba-3.2.2.dist-info/licenses/LICENSE.md
neo_mamba-3.2.2.dist-info/METADATA
neo_mamba-3.2.2.dist-info/WHEEL
neo_mamba-3.2.2.dist-info/top_level.txt
neo_mamba-3.2.2.dist-info/RECORD
