Metadata-Version: 2.4
Name: neo-mamba
Version: 3.2.2
Summary: Python SDK for the NEO 3 blockchain
Author-email: Erik van den Brink <erik@coz.io>
Maintainer-email: Erik van den Brink <erik@coz.io>
License-Expression: MIT
Project-URL: repository, https://github.com/CityOfZion/neo-mamba
Project-URL: documentation, https://mamba.coz.io/
Keywords: NEO,NEO3,blockchain,SDK
Requires-Python: <3.15,>=3.13.0
License-File: LICENSE.md
Requires-Dist: aiodns==3.6.1
Requires-Dist: aiohttp~=3.13
Requires-Dist: base58==2.1.1
Requires-Dist: bitarray==3.8.0
Requires-Dist: Events==0.5
Requires-Dist: jsonschema==4.25.1
Requires-Dist: lz4==4.4.5
Requires-Dist: neo3crypto==0.4.5
Requires-Dist: netaddr==1.3.0
Requires-Dist: orjson>=3.11.5
Requires-Dist: pycryptodome==3.23.0
Requires-Dist: pybiginteger==1.3.5
Requires-Dist: pybiginteger-stubs==1.3.5
Provides-Extra: dev
Requires-Dist: aioresponses==0.7.6; extra == "dev"
Requires-Dist: black==25.12.0; extra == "dev"
Requires-Dist: build==0.10.0; extra == "dev"
Requires-Dist: bump-my-version==0.12.0; extra == "dev"
Requires-Dist: coverage>=7.3.2; extra == "dev"
Requires-Dist: docutils==0.17.1; extra == "dev"
Requires-Dist: mypy==1.7.1; extra == "dev"
Requires-Dist: mypy-extensions==1.0.0; extra == "dev"
Provides-Extra: docs
Requires-Dist: mkdocs==1.4.1; extra == "docs"
Requires-Dist: mkdocs-material==8.5.7; extra == "docs"
Requires-Dist: mkdocs-material-extensions==1.1; extra == "docs"
Requires-Dist: mkapi-fix-coz==0.1.0; extra == "docs"
Provides-Extra: examples
Requires-Dist: boa-test-constructor==v0.4.0; extra == "examples"
Dynamic: license-file
